{
  "-2": ["rectifier techologies", "brave bison", "starvest", "starvest.ru", "starvest.com"],
  "-1": ["образование","бакалавр", "магистр", "диплом", "потребительская корзина", "госуслуги", "специалитет"],
  "0": ["французский бульдог"],
  "1": ["уход за кожей", "умывание", "крем", "лицо", "spf", "ретинол", "косметика", "кожа"],
  "2": ["СП35.13330.2010", "мосты", "трубы", "строительство", "бетон"],
  "3": ["rmr", "red_mad_robot", "red mad robot"],
  "4": ["telegram", "телеграм", "тг"],
  "5": ["michelin", "мишлен", "рейтинг ресторанов"],
  "6": ["Трудовой кодекс", "тк рф", "трудовой договор", "мрот", "зарплата", "отпуск"],
  "7": ["world class", "фитнес", "спорт", "абонемент", "тренировки"],
  "8": ["оплата услуг", "дом ру", "мтс банк", "кредит", "вклад"]
}
